{"version":1,"resource":"file:///home/ever/Desktop/dev/apps/support-decisions/app.json","entries":[{"id":"eNuJ.json","timestamp":1653838826829},{"id":"rD65.json","timestamp":1653838914438},{"id":"hfzs.json","timestamp":1653838928382},{"id":"l9sF.json","timestamp":1653838958926},{"id":"9Hj0.json","timestamp":1653838974230},{"id":"Vyt3.json","timestamp":1653839052903},{"id":"R62U.json","timestamp":1653839225215},{"id":"o95I.json","timestamp":1653839274695},{"id":"ykbr.json","timestamp":1653839444441},{"id":"F1Jd.json","timestamp":1653839470464},{"id":"QGSE.json","timestamp":1653839494511},{"id":"b5fQ.json","timestamp":1653839508855},{"id":"p70P.json","timestamp":1653839520615},{"id":"GAlh.json","timestamp":1653839573428},{"id":"aeHv.json","timestamp":1653839660698},{"id":"UBPc.json","timestamp":1653839689658},{"id":"n4Gu.json","timestamp":1653839702149},{"id":"MTri.json","timestamp":1653839828051},{"id":"15fb.json","timestamp":1653839905237},{"id":"av2z.json","timestamp":1653839922575},{"id":"Jrhe.json","timestamp":1653840108502},{"id":"bII9.json","timestamp":1653840222388},{"id":"wWxV.json","timestamp":1653840255859},{"id":"W287.json","timestamp":1653840342573},{"id":"pmQf.json","timestamp":1653841296502},{"id":"7hCE.json","timestamp":1653841347306},{"id":"AeZ4.json","timestamp":1653841376559},{"id":"rgUm.json","timestamp":1653841418918},{"id":"Z73D.json","timestamp":1653842066111},{"id":"QH70.json","timestamp":1653842208034},{"id":"hobD.json","timestamp":1653842323380},{"id":"LWwP.json","timestamp":1653846815828},{"id":"LFxV.json","timestamp":1653846925598},{"id":"h874.json","timestamp":1653847247540},{"id":"XscN.json","timestamp":1653847376147},{"id":"t2aP.json","timestamp":1653847452432},{"id":"wWIQ.json","timestamp":1653848809250},{"id":"HApr.json","timestamp":1653848891124},{"id":"8Klu.json","timestamp":1653850260192},{"id":"TKlw.json","timestamp":1653850276681},{"id":"NGvA.json","timestamp":1653850389398},{"id":"B7eE.json","timestamp":1653850431287},{"id":"LShO.json","timestamp":1653850477751},{"id":"gLZi.json","timestamp":1653850571386},{"id":"TGgG.json","timestamp":1653850584716},{"id":"vICf.json","timestamp":1653932685898},{"id":"nTVQ.json","timestamp":1653946596938},{"id":"Iesb.json","timestamp":1653949396939},{"id":"kWCA.json","timestamp":1653950693263},{"id":"pbPy.json","timestamp":1653962108541}]}